minnesota_immunization_core/__init__.py
minnesota_immunization_core/etl_workflow.py
minnesota_immunization_core/extract.py
minnesota_immunization_core/load.py
minnesota_immunization_core/pipeline_factory.py
minnesota_immunization_core/py.typed
minnesota_immunization_core/transform.py
minnesota_immunization_core/aisr/__init__.py
minnesota_immunization_core/aisr/actions.py
minnesota_immunization_core/aisr/authenticate.py
minnesota_immunization_core-0.1.3.dist-info/METADATA
minnesota_immunization_core-0.1.3.dist-info/WHEEL
minnesota_immunization_core-0.1.3.dist-info/RECORD
