Metadata-Version: 2.4
Name: minnesota-immunization-core
Version: 0.1.3
Summary: Core library for Minnesota immunization records processing
Author-email: Dillon O'Leary <doleary@wisc.edu>
License: GPL-3.0-or-later
Keywords: aisr,etl,immunization,minnesota,vaccination
Classifier: Development Status :: 3 - Alpha
Classifier: Intended Audience :: Developers
Classifier: Intended Audience :: Healthcare Industry
Classifier: License :: OSI Approved :: GNU General Public License v3 or later (GPLv3+)
Classifier: Programming Language :: Python :: 3
Classifier: Programming Language :: Python :: 3.11
Classifier: Programming Language :: Python :: 3.12
Classifier: Topic :: Scientific/Engineering :: Medical Science Apps.
Classifier: Topic :: Software Development :: Libraries :: Python Modules
Requires-Python: >=3.11
Requires-Dist: beautifulsoup4
Requires-Dist: httpx>=0.28.1
Requires-Dist: pandas
Requires-Dist: requests
Requires-Dist: tenacity>=9.1.2
Provides-Extra: dev
Requires-Dist: faker; extra == 'dev'
Requires-Dist: fastapi; extra == 'dev'
Requires-Dist: pytest; extra == 'dev'
Requires-Dist: pytest-cov; extra == 'dev'
Requires-Dist: python-multipart; extra == 'dev'
Requires-Dist: ruff; extra == 'dev'
Requires-Dist: types-requests; extra == 'dev'
Requires-Dist: uvicorn; extra == 'dev'
